cfq/__init__.py
cfq-0.1.2.dist-info/licenses/LICENSE
cfq-0.1.2.dist-info/METADATA
cfq-0.1.2.dist-info/WHEEL
cfq-0.1.2.dist-info/top_level.txt
cfq-0.1.2.dist-info/RECORD
