Metadata-Version: 2.4
Name: cfq
Version: 0.1.2
Summary: A high-level Cloudflare Queues consumer library for Python
Requires-Python: >=3.13
License-File: LICENSE
Requires-Dist: cloudflare>=4.3.1
Requires-Dist: tenacity>=9.1.2
Dynamic: license-file
